.
CHANGELOG.md
LICENSE
MANIFEST.in
README.rst
setup.cfg
setup.py
/
pandoc_beamer_notes/__init__.py
pandoc_beamer_notes/pandoc-beamer-notes.py
pandoc_beamer_notes/pandoc_beamer_notes.py
pandoc_beamer_notes.egg-info/PKG-INFO
pandoc_beamer_notes.egg-info/SOURCES.txt
pandoc_beamer_notes.egg-info/dependency_links.txt
pandoc_beamer_notes.egg-info/entry_points.txt
pandoc_beamer_notes.egg-info/requires.txt
pandoc_beamer_notes.egg-info/top_level.txt