Metadata-Version: 1.1
Name: pandoc-beamer-notes
Version: 0.1.2
Summary: A pandoc filter to allow a markdown way of using notes for latex beamer presentations.
Home-page: https://github.com/shoeffner/pandoc-beamer-notes
Author: Sebastian Höffner
Author-email: info@sebastian-hoeffner.de
License: MIT
Download-URL: https://github.com/shoeffner/pandoc-beamer-notes/tarball/0.1.2
Keywords: pandoc,beamer,notes,filter
Platform: UNKNOWN
Classifier: Development Status :: 7 - Inactive
Classifier: Intended Audience :: Science/Research
Classifier: License :: OSI Approved :: MIT License
Classifier: Natural Language :: English
Classifier: Programming Language :: Python :: 3.6
Classifier: Topic :: Text Processing :: Filters
